<?xml version="1.0"?>
<!--Moose2Model Layout data, visit moose2model.org on how to use this file-->
<elements>
    <version>v1.3.2</version>
    <suppressed>packageBox</suppressed>
    <scope>method</scope>
    <element>
        <type>FAMIXClass</type>
        <class>RWDiagramAppearanceChanger</class>
        <x>-49.0</x>
        <y>204.0</y>
    </element>
    <element>
        <type>FAMIXMethod</type>
        <class>RWDiagramLayout</class>
        <method>readFromStream:message:</method>
        <x>-487.0</x>
        <y>450.0</y>
    </element>
    <element>
        <type>FAMIXMethod</type>
        <class>MooseModel</class>
        <method>moose2ModelReadLayout2</method>
        <x>-570.0</x>
        <y>281.0</y>
    </element>
    <element>
        <type>FAMIXMethod</type>
        <class>RWDiagram</class>
        <method>refresh</method>
        <hasClassScope>true</hasClassScope>
        <x>-313.0</x>
        <y>115.0</y>
    </element>
    <element>
        <type>FAMIXMethod</type>
        <class>RWDiagramACTSuppressOthers</class>
        <method>=</method>
        <x>79.0</x>
        <y>129.0</y>
    </element>
    <element>
        <type>FAMIXClass</type>
        <class>RWDiagramACDStandard</class>
        <x>97.0</x>
        <y>220.0</y>
    </element>
    <element>
        <type>FAMIXMethod</type>
        <class>RWDiagram</class>
        <method>path</method>
        <hasClassScope>true</hasClassScope>
        <x>-364.0</x>
        <y>135.0</y>
    </element>
    <element>
        <type>FAMIXPackage</type>
        <package>Moose-Core</package>
        <x>901.5</x>
        <y>267.0</y>
    </element>
    <element>
        <type>FAMIXPackage</type>
        <package>Moose2Model</package>
        <x>1306.5</x>
        <y>639.5</y>
    </element>
    <element>
        <type>FAMIXMethod</type>
        <class>RWDiagram</class>
        <method>readLayout:ofMooseModel:expliciteStream:</method>
        <hasClassScope>true</hasClassScope>
        <x>-381.0</x>
        <y>162.0</y>
        <ACTSuppressOthers>
            <type>ACDStandard</type>
            <includeMe>true</includeMe>
            <usedByLayers>1</usedByLayers>
            <usingLayers>1</usingLayers>
        </ACTSuppressOthers>
    </element>
    <element>
        <type>FAMIXMethod</type>
        <class>RWDiagram</class>
        <method>readFromPath:</method>
        <hasClassScope>true</hasClassScope>
        <x>-474.0</x>
        <y>152.0</y>
        <comment><![CDATA[Obsolete]]>
        </comment>
    </element>
    <element>
        <type>FAMIXMethod</type>
        <class>RWDiagramSimpleGui</class>
        <method>getInstance</method>
        <hasClassScope>true</hasClassScope>
        <x>74.0</x>
        <y>313.0</y>
    </element>
    <element>
        <type>FAMIXMethod</type>
        <class>RWDiagram</class>
        <method>currentLayoutName</method>
        <hasClassScope>true</hasClassScope>
        <x>-392.0</x>
        <y>137.0</y>
    </element>
    <element>
        <type>FAMIXMethod</type>
        <class>M2MFrontend</class>
        <method>refresh</method>
        <x>293.0</x>
        <y>489.0</y>
    </element>
    <element>
        <type>FAMIXMethod</type>
        <class>RWDiagramEditor</class>
        <method>readFromFile:</method>
        <x>-325.0</x>
        <y>345.0</y>
        <comment><![CDATA[Obsolete]]>
        </comment>
        <commentx>-256.0</commentx>
        <commenty>506.0</commenty>
        <ACTSuppressOthers>
            <type>ACDStandard</type>
            <includeMe>true</includeMe>
            <usedByLayers>1</usedByLayers>
            <usingLayers>1</usingLayers>
        </ACTSuppressOthers>
    </element>
    <element>
        <type>FAMIXMethod</type>
        <class>RWDiagramEditor</class>
        <method>uniqueInstance</method>
        <hasClassScope>true</hasClassScope>
        <x>-123.0</x>
        <y>350.0</y>
    </element>
    <element>
        <type>FAMIXMethod</type>
        <class>RWDiagramElement</class>
        <method>refresh</method>
        <x>38.0</x>
        <y>52.0</y>
    </element>
    <element>
        <type>FAMIXClass</type>
        <class>FAMIXClassGroup</class>
        <x>-81.0</x>
        <y>438.0</y>
    </element>
    <element>
        <type>FAMIXMethod</type>
        <class>RWDiagramLayout</class>
        <method>refresh</method>
        <x>-487.0</x>
        <y>425.0</y>
    </element>
    <element>
        <type>FAMIXMethod</type>
        <class>RWDiagramEditor</class>
        <method>settings</method>
        <x>-263.0</x>
        <y>297.0</y>
    </element>
    <element>
        <type>FAMIXMethod</type>
        <class>RWDiagramEditor</class>
        <method>currentLayout</method>
        <x>-222.0</x>
        <y>323.0</y>
    </element>
    <element>
        <type>FAMIXClass</type>
        <class>RWDiagramACTHighlight</class>
        <x>-61.0</x>
        <y>95.0</y>
    </element>
    <element>
        <type>FAMIXMethod</type>
        <class>MooseModel</class>
        <method>moose2ModelDependency</method>
        <x>-551.0</x>
        <y>261.0</y>
        <comment><![CDATA[Display a diagram]]>
        </comment>
        <commentx>-562.0</commentx>
        <commenty>210.0</commenty>
        <ACTSuppressOthers>
            <type>ACDStandard</type>
            <includeMe>true</includeMe>
            <usedByLayers>1</usedByLayers>
            <usingLayers>1</usingLayers>
        </ACTSuppressOthers>
    </element>
    <element>
        <type>FAMIXMethod</type>
        <class>RWDiagramEditor</class>
        <method>refreshLayout:</method>
        <x>-193.0</x>
        <y>311.0</y>
    </element>
    <element>
        <type>FAMIXPackage</type>
        <package>Famix-Extensions</package>
        <x>703.5</x>
        <y>254.5</y>
    </element>
    <element>
        <type>FAMIXPackage</type>
        <package>RWMooseDiagram</package>
        <x>304.5</x>
        <y>323.0</y>
    </element>
    <element>
        <type>FAMIXMethod</type>
        <class>RWDiagramAppearanceChanger</class>
        <method>=</method>
        <x>-49.0</x>
        <y>194.0</y>
    </element>
    <element>
        <type>FAMIXMethod</type>
        <class>RWDiagramEditor</class>
        <method>readFromFile:expliciteStream:</method>
        <x>-250.0</x>
        <y>350.0</y>
        <comment><![CDATA[Reads filestream, uses stream provided when not nil<br>This is needed for tests]]>
        </comment>
    </element>
    <element>
        <type>FAMIXClass</type>
        <class>RWDiagram</class>
        <x>-356.0</x>
        <y>173.0</y>
    </element>
    <element>
        <type>FAMIXMethod</type>
        <class>RWDiagramLayout</class>
        <method>mooseID</method>
        <x>-468.0</x>
        <y>436.0</y>
    </element>
    <element>
        <type>FAMIXMethod</type>
        <class>RWDiagramLayoutManager</class>
        <method>layoutsOfCurrentPath</method>
        <x>-583.0</x>
        <y>75.0</y>
    </element>
    <element>
        <type>FAMIXMethod</type>
        <class>MooseModel</class>
        <method>moose2ModelDependencyInfo</method>
        <x>-552.0</x>
        <y>306.0</y>
        <comment><![CDATA[Display a diagram and highlight elements with appearance changer]]>
        </comment>
        <commentx>-586.0</commentx>
        <commenty>359.0</commenty>
        <ACTSuppressOthers>
            <type>ACDStandard</type>
            <includeMe>true</includeMe>
            <usedByLayers>1</usedByLayers>
            <usingLayers>1</usingLayers>
        </ACTSuppressOthers>
    </element>
    <element>
        <type>FAMIXMethod</type>
        <class>FAMIXClassGroup</class>
        <method>generateMoose2ModelDiagramOfMooseModel:</method>
        <x>-79.0</x>
        <y>427.0</y>
    </element>
    <element>
        <type>FAMIXMethod</type>
        <class>RWDiagramNoPackage</class>
        <method>mooseID</method>
        <x>-577.0</x>
        <y>16.0</y>
    </element>
    <element>
        <type>FAMIXMethod</type>
        <class>RWDiagramElement</class>
        <method>refresh</method>
        <hasClassScope>true</hasClassScope>
        <x>38.0</x>
        <y>77.0</y>
    </element>
    <element>
        <type>FAMIXMethod</type>
        <class>MooseModel</class>
        <method>moose2ModelReadLayoutExpliciteStream:</method>
        <x>-671.0</x>
        <y>270.0</y>
        <ACTSuppressOthers>
            <type>ACDStandard</type>
            <includeMe>true</includeMe>
            <usedByLayers>1</usedByLayers>
            <usingLayers>1</usingLayers>
        </ACTSuppressOthers>
    </element>
    <element>
        <type>FAMIXClass</type>
        <class>MooseModel</class>
        <x>-608.0</x>
        <y>304.0</y>
    </element>
    <element>
        <type>FAMIXClass</type>
        <class>RWDiagramSimpleGui</class>
        <x>86.0</x>
        <y>310.0</y>
    </element>
    <element>
        <type>FAMIXClass</type>
        <class>M2MFrontendDemo</class>
        <x>135.0</x>
        <y>383.0</y>
    </element>
    <element>
        <type>FAMIXMethod</type>
        <class>RWDiagramSimpleGui</class>
        <method>redrawMe</method>
        <x>71.0</x>
        <y>288.0</y>
    </element>
    <element>
        <type>FAMIXMethod</type>
        <class>RWDiagram</class>
        <method>readFromFile:expliciteStream:</method>
        <hasClassScope>true</hasClassScope>
        <x>-525.0</x>
        <y>186.0</y>
    </element>
    <element>
        <type>FAMIXMethod</type>
        <class>RWDiagramSettings</class>
        <method>displayFormatter:</method>
        <x>-202.0</x>
        <y>162.0</y>
    </element>
    <element>
        <type>FAMIXClass</type>
        <class>RWDiagramLayout</class>
        <x>-468.0</x>
        <y>448.0</y>
    </element>
    <element>
        <type>FAMIXMethod</type>
        <class>RWDiagramLayout</class>
        <method>mooseID:</method>
        <x>-452.0</x>
        <y>425.0</y>
    </element>
    <element>
        <type>FAMIXMethod</type>
        <class>MooseModel</class>
        <method>moose2ModelReadLayout</method>
        <x>-686.0</x>
        <y>224.0</y>
        <ACTSuppressOthers>
            <type>ACDStandard</type>
            <includeMe>true</includeMe>
            <usedByLayers>1</usedByLayers>
            <usingLayers>1</usingLayers>
        </ACTSuppressOthers>
    </element>
    <element>
        <type>FAMIXClass</type>
        <class>RWDiagramElement</class>
        <x>50.0</x>
        <y>74.0</y>
    </element>
    <element>
        <type>FAMIXMethod</type>
        <class>RWDiagramEditor</class>
        <method>currentLayoutName:</method>
        <x>-230.0</x>
        <y>273.0</y>
    </element>
    <element>
        <type>FAMIXClass</type>
        <class>RWDiagramACTSuppressOthers</class>
        <x>79.0</x>
        <y>140.0</y>
    </element>
    <element>
        <type>FAMIXMethod</type>
        <class>RWDiagram</class>
        <method>readLayout:ofMooseModel:</method>
        <hasClassScope>true</hasClassScope>
        <x>-307.0</x>
        <y>193.0</y>
        <ACTSuppressOthers>
            <type>ACDStandard</type>
            <includeMe>true</includeMe>
            <usedByLayers>1</usedByLayers>
            <usingLayers>1</usingLayers>
        </ACTSuppressOthers>
    </element>
    <element>
        <type>FAMIXClass</type>
        <class>M2MFrontend</class>
        <x>293.0</x>
        <y>500.0</y>
    </element>
    <element>
        <type>FAMIXMethod</type>
        <class>M2MFrontendDemo</class>
        <method>refresh</method>
        <x>135.0</x>
        <y>373.0</y>
    </element>
    <element>
        <type>FAMIXMethod</type>
        <class>RWDiagram</class>
        <method>readFromPath:expliciteStream:</method>
        <hasClassScope>true</hasClassScope>
        <x>-489.0</x>
        <y>118.0</y>
        <ACTSuppressOthers>
            <type>ACDStandard</type>
            <includeMe>true</includeMe>
            <usedByLayers>1</usedByLayers>
            <usingLayers>1</usingLayers>
        </ACTSuppressOthers>
    </element>
    <element>
        <type>FAMIXMethod</type>
        <class>RWDiagramEditor</class>
        <method>lastUsedClassGroup:</method>
        <x>-148.0</x>
        <y>283.0</y>
    </element>
    <element>
        <type>FAMIXMethod</type>
        <class>RWDiagram</class>
        <method>readFromFile:</method>
        <hasClassScope>true</hasClassScope>
        <x>-458.0</x>
        <y>192.0</y>
        <comment><![CDATA[Obsolete]]>
        </comment>
    </element>
    <element>
        <type>FAMIXMethod</type>
        <class>RWDiagram</class>
        <method>currentLayoutName:</method>
        <hasClassScope>true</hasClassScope>
        <x>-257.0</x>
        <y>116.0</y>
    </element>
    <element>
        <type>FAMIXMethod</type>
        <class>RWDiagramElement</class>
        <method>=</method>
        <x>68.0</x>
        <y>19.0</y>
    </element>
    <element>
        <type>FAMIXMethod</type>
        <class>RWDiagramSimpleGui</class>
        <method>refresh</method>
        <hasClassScope>true</hasClassScope>
        <x>86.0</x>
        <y>300.0</y>
    </element>
    <element>
        <type>FAMIXClass</type>
        <class>RWDiagramEditor</class>
        <x>-202.0</x>
        <y>323.0</y>
    </element>
    <element>
        <type>FAMIXClass</type>
        <class>RWDiagramLayoutManager</class>
        <x>-584.0</x>
        <y>85.0</y>
    </element>
    <element>
        <type>FAMIXClass</type>
        <class>RWDiagramSettings</class>
        <x>-202.0</x>
        <y>173.0</y>
    </element>
    <element>
        <type>FAMIXMethod</type>
        <class>RWDiagramEditor</class>
        <method>refresh</method>
        <hasClassScope>true</hasClassScope>
        <x>-100.0</x>
        <y>308.0</y>
    </element>
    <element>
        <type>FAMIXMethod</type>
        <class>RWDiagramACDStandard</class>
        <method>=</method>
        <x>97.0</x>
        <y>210.0</y>
    </element>
    <element>
        <type>FAMIXClass</type>
        <class>RWDiagramNoPackage</class>
        <x>-577.0</x>
        <y>26.0</y>
    </element>
    <element>
        <type>FAMIXMethod</type>
        <class>RWDiagramACTHighlight</class>
        <method>=</method>
        <x>-61.0</x>
        <y>84.0</y>
    </element>
    <element>
        <type>FAMIXMethod</type>
        <class>RWDiagramEditor</class>
        <method>currentLayoutName</method>
        <x>-305.0</x>
        <y>287.0</y>
    </element>
</elements>